[
    {
        "id": 1,
        "title": "Компьютерная диагностика",
        "description": "Полная диагностика вашего автомобиля с использованием новейших технологий.",
        "image": "img/diagnostika.jpg"
    },
    {
        "id": 2,
        "title": "Эндоскопия двигателя",
        "description": "Проведение эндоскопии двигателя для выявления проблем.",
        "image": "img/endoscopy.jpg"
    },
    {
        "id": 3,
        "title": "Ремонт подвески",
        "description": "Профессиональный ремонт подвески для вашего автомобиля.",
        "image": "img/suspension.jpg"
    },
    {
        "id": 4,
        "title": "Замена масла",
        "description": "Качественная замена масла для продления срока службы вашего двигателя.",
        "image": "img/oil-change.jpg"
    },
    {
        "id": 5,
        "title": "Шиномонтаж",
        "description": "Замена и балансировка шин для безопасного и комфортного вождения.",
        "image": "img/tire-service.jpg"
    }
]
